{
  "cookies": [
    {
      "name": "AC_SF_8CEFDA09D5",
      "value": "fb1e7ebf0a2217f4c1830eb5c10ceeae",
      "domain": "automationteststore.com",
      "path": "/",
      "expires": -1,
      "httpOnly": true,
      "secure": true,
      "sameSite": "Lax"
    },
    {
      "name": "language",
      "value": "en",
      "domain": "automationteststore.com",
      "path": "/",
      "expires": 1710542442.303408,
      "httpOnly": false,
      "secure": true,
      "sameSite": "Lax"
    },
    {
      "name": "currency",
      "value": "USD",
      "domain": "automationteststore.com",
      "path": "/",
      "expires": 1710542442.303486,
      "httpOnly": false,
      "secure": true,
      "sameSite": "Lax"
    }
  ],
  "origins": []
}